super3/__init__.py
super3/__main__.py
super3/main.py
super3-0.1.5.dist-info/entry_points.txt
super3-0.1.5.dist-info/WHEEL
super3-0.1.5.dist-info/METADATA
super3-0.1.5.dist-info/RECORD
