Metadata-Version: 2.1
Name: super3
Version: 0.1.5
Summary: 
Author: Your Name
Author-email: you@example.com
Requires-Python: >=3.6,<4.0
Classifier: Programming Language :: Python :: 3
Classifier: Programming Language :: Python :: 3.6
Classifier: Programming Language :: Python :: 3.7
Classifier: Programming Language :: Python :: 3.8
Requires-Dist: astor (>=0.8.1,<0.9.0)
Requires-Dist: attrs (>=19.3.0,<20.0.0)
Requires-Dist: click (>=7.1.2,<8.0.0)
